{
  "version": "0.2.23",
  "flags": {},
  "shapes": [
    {
      "label": "target",
      "text": "肉",
      "points": [
        [
          143.0,
          10.0
        ],
        [
          207.0,
          77.0
        ]
      ],
      "group_id": null,
      "shape_type": "rectangle",
      "flags": {}
    },
    {
      "label": "target",
      "text": "牛",
      "points": [
        [
          252.0,
          118.0
        ],
        [
          313.0,
          180.0
        ]
      ],
      "group_id": null,
      "shape_type": "rectangle",
      "flags": {}
    },
    {
      "label": "target",
      "text": "味",
      "points": [
        [
          16.0,
          144.0
        ],
        [
          79.0,
          210.0
        ]
      ],
      "group_id": null,
      "shape_type": "rectangle",
      "flags": {}
    },
    {
      "label": "target",
      "text": "川",
      "points": [
        [
          103.0,
          203.0
        ],
        [
          169.0,
          267.0
        ]
      ],
      "group_id": null,
      "shape_type": "rectangle",
      "flags": {}
    },
    {
      "label": "char",
      "text": "肉",
      "points": [
        [
          83.0,
          349.0
        ],
        [
          104.0,
          377.0
        ]
      ],
      "group_id": null,
      "shape_type": "rectangle",
      "flags": {}
    },
    {
      "label": "char",
      "text": "牛",
      "points": [
        [
          56.0,
          348.0
        ],
        [
          80.0,
          376.0
        ]
      ],
      "group_id": null,
      "shape_type": "rectangle",
      "flags": {}
    },
    {
      "label": "char",
      "text": "味",
      "points": [
        [
          29.0,
          348.0
        ],
        [
          60.0,
          378.0
        ]
      ],
      "group_id": null,
      "shape_type": "rectangle",
      "flags": {}
    },
    {
      "label": "char",
      "text": "川",
      "points": [
        [
          1.0,
          349.0
        ],
        [
          32.0,
          378.0
        ]
      ],
      "group_id": null,
      "shape_type": "rectangle",
      "flags": {}
    }
  ],
  "imagePath": "img_3287.jpg",
  "imageData": null,
  "imageHeight": 384,
  "imageWidth": 344,
  "text": ""
}