{
  "version": "0.2.23",
  "flags": {},
  "shapes": [
    {
      "label": "target",
      "text": "黑",
      "points": [
        [
          189.0,
          120.0
        ],
        [
          253.0,
          184.0
        ]
      ],
      "group_id": null,
      "shape_type": "rectangle",
      "flags": {}
    },
    {
      "label": "target",
      "text": "茶",
      "points": [
        [
          250.0,
          197.0
        ],
        [
          315.0,
          261.0
        ]
      ],
      "group_id": null,
      "shape_type": "rectangle",
      "flags": {}
    },
    {
      "label": "char",
      "text": "黑",
      "points": [
        [
          1.0,
          352.0
        ],
        [
          28.0,
          379.0
        ]
      ],
      "group_id": null,
      "shape_type": "rectangle",
      "flags": {}
    },
    {
      "label": "char",
      "text": "茶",
      "points": [
        [
          27.0,
          349.0
        ],
        [
          55.0,
          376.0
        ]
      ],
      "group_id": null,
      "shape_type": "rectangle",
      "flags": {}
    }
  ],
  "imagePath": "img_3508.jpg",
  "imageData": null,
  "imageHeight": 384,
  "imageWidth": 344,
  "text": ""
}